deputy/__init__.py
deputy/deputy.py
deputy/deputy_test.py
google_deputy_api_python_client-0.0.1.dist-info/LICENSE
google_deputy_api_python_client-0.0.1.dist-info/METADATA
google_deputy_api_python_client-0.0.1.dist-info/WHEEL
google_deputy_api_python_client-0.0.1.dist-info/top_level.txt
google_deputy_api_python_client-0.0.1.dist-info/RECORD
