Metadata-Version: 2.1
Name: google-deputy-api-python-client
Version: 0.0.1
Summary: A pythonic library for interacting with Deputy.com's API.
Home-page: https://github.com/google/deputy-api-python-client
Author: Google
License: UNKNOWN
Platform: UNKNOWN
Classifier: Programming Language :: Python :: 3
Classifier: License :: OSI Approved :: Apache Software License
Classifier: Operating System :: OS Independent
Requires-Python: >=3.6
Requires-Dist: absl-py
Requires-Dist: attrs (>=19)
Requires-Dist: parameterized
Requires-Dist: python-dateutil
Requires-Dist: pytype
Requires-Dist: urllib3
